heatmap3Dlib/__init__.py
heatmap3Dlib/plot3D.py
heatmap3Dlib-0.2.2.dist-info/LICENSE
heatmap3Dlib-0.2.2.dist-info/METADATA
heatmap3Dlib-0.2.2.dist-info/WHEEL
heatmap3Dlib-0.2.2.dist-info/top_level.txt
heatmap3Dlib-0.2.2.dist-info/RECORD
