Metadata-Version: 2.1
Name: heatmap3Dlib
Version: 0.2.2
Summary: 3D heatmap plot library
Home-page: UNKNOWN
Author: Matteo Biviano
License: GPLv3
Platform: UNKNOWN
License-File: LICENSE
Requires-Dist: matplotlib
Requires-Dist: pandas
Requires-Dist: numpy
